create_tox_app/__init__.py
create_tox_app/__main__.py
create_tox_app/exit_codes.py
create_tox_app/generator.py
create_tox_app/templates.py
create_tox_app-1.0.2.dist-info/LICENSE
create_tox_app-1.0.2.dist-info/METADATA
create_tox_app-1.0.2.dist-info/WHEEL
create_tox_app-1.0.2.dist-info/entry_points.txt
create_tox_app-1.0.2.dist-info/top_level.txt
create_tox_app-1.0.2.dist-info/RECORD
