Metadata-Version: 2.1
Name: create-tox-app
Version: 1.0.2
Summary: A wrapper that creates a tox env with the minimal setup for a Python app.
Home-page: https://github.com/wozniakpl/create-tox-app.git
Author: Bartosz Woźniak
Author-email: bwozniakdev@protonmail.com
Classifier: Intended Audience :: Developers
Classifier: License :: OSI Approved :: MIT License
Classifier: Operating System :: OS Independent
Classifier: Natural Language :: English
Classifier: Programming Language :: Python
License-File: LICENSE
